<?xml version="1.0" encoding="UTF-8"?>
<rendertheme version="4">

    <!-- 各類道路 -->
    <rule e="way" k="highway" v="*">
        <!-- 小街道 -->
        <rule e="way" k="highway" v="service|unclassified|residential">
            <rule e="way" k="*" v="*" zoom-min="16" zoom-max="17">
                <pathText k="name" font-size="10" stroke="#ffffff" stroke-width="2.0" />
            </rule>
            <rule e="way" k="*" v="*" zoom-min="14" zoom-max="14">
                <line stroke="#d0d0d0" stroke-width="0.2" />
            </rule>
            <rule e="way" k="*" v="*" zoom-min="15" zoom-max="15">
                <line stroke="#707070" stroke-width="0.6" />
                <line stroke="#ffffff" stroke-width="0.5" />
            </rule>
            <rule e="way" k="*" v="*" zoom-min="16" zoom-max="16">
                <line stroke="#707070" stroke-width="0.7" />
                <line stroke="#ffffff" stroke-width="0.6" />
            </rule>
            <rule e="way" k="*" v="*" zoom-min="17" zoom-max="17">
                <line stroke="#707070" stroke-width="0.8" />
                <line stroke="#ffffff" stroke-width="0.7" />
            </rule>
        </rule>

        <!-- 一般重要道路 -->
        <rule e="way" k="highway" v="secondary|secondary_link|tertiary|tertiary_link">
            <!-- 非隧道段 -->
            <rule e="way" k="tunnel" v="~|no|false">
                <rule e="way" k="*" v="*" zoom-min="12" zoom-max="12">
                    <line stroke="#e7e790" stroke-width="1.2" />
                </rule>
                <rule e="way" k="*" v="*" zoom-min="13" zoom-max="15">
                    <line stroke="#707070" stroke-width="1.2" />
                    <line stroke="#f0f0a0" stroke-width="1.0" />
                </rule>
                <rule e="way" k="*" v="*" zoom-min="16" zoom-max="16">
                    <line stroke="#707070" stroke-width="0.9" />
                    <line stroke="#f0f0a0" stroke-width="0.7" />
                </rule>
                <rule e="way" k="*" v="*" zoom-min="17" zoom-max="17">
                    <line stroke="#707070" stroke-width="1.0" />
                    <line stroke="#f0f0a0" stroke-width="0.8" />
                </rule>
            </rule>
            <!-- 隧道段 / 檢查點：復興北路地下道-->
            <rule e="way" k="tunnel" v="true|yes">
                <rule e="way" k="*" v="*" zoom-min="12" zoom-max="12">
                    <line stroke="#e7e790" stroke-width="1.2" />
                </rule>
                <rule e="way" k="*" v="*" zoom-min="13" zoom-max="13">
                    <line stroke="#f0f0a0" stroke-width="1.1" stroke-dasharray="2,4" stroke-linecap="square" />
                </rule>
                <rule e="way" k="*" v="*" zoom-min="14" zoom-max="14">
                    <line stroke="#f0f0a0" stroke-width="1.0" stroke-dasharray="6,6" stroke-linecap="square" />
                </rule>
                <rule e="way" k="*" v="*" zoom-min="15" zoom-max="15">
                    <line stroke="#f0f0a0" stroke-width="0.9" stroke-dasharray="8,8" stroke-linecap="square" />
                </rule>
                <rule e="way" k="*" v="*" zoom-min="16" zoom-max="16">
                    <line stroke="#f0f0a0" stroke-width="0.8" stroke-dasharray="10,10" stroke-linecap="square" />
                </rule>
                <rule e="way" k="*" v="*" zoom-min="17" zoom-max="17">
                    <line stroke="#f0f0a0" stroke-width="0.7" stroke-dasharray="12,12" stroke-linecap="square" />
                </rule>
            </rule>
            <!-- 除錯用 -->
            <rule e="way" k="*" v="*" zoom-min="10" zoom-max="18">
                <pathText k="name" font-size="10" stroke="#ffffff" stroke-width="2.0" />
            </rule>
        </rule>

        <!-- 省道 -->
        <rule e="way" k="highway" v="primary|primary_link">
            <rule e="way" k="*" v="*" zoom-min="8" zoom-max="18">
                <pathText k="name" fill="#000000" font-size="10" stroke="#ffffff" stroke-width="2.0" />
            </rule>
            <!-- 非隧道段 -->
            <rule e="way" k="tunnel" v="~|no|false">
                <rule e="way" k="*" v="*" zoom-min="9" zoom-max="9">
                    <line stroke="#70d0ff" stroke-width="0.6" />
                </rule>
                <rule e="way" k="*" v="*" zoom-min="10" zoom-max="12">
                    <line stroke="#70d0ff" stroke-width="0.9" />
                </rule>
                <rule e="way" k="*" v="*" zoom-min="13" zoom-max="15">
                    <line stroke="#707070" stroke-width="1.2" />
                    <line stroke="#70d0ff" stroke-width="1.0" />
                </rule>
                <rule e="way" k="*" v="*" zoom-min="16" zoom-max="16">
                    <line stroke="#707070" stroke-width="0.9" />
                    <line stroke="#70d0ff" stroke-width="0.7" />
                </rule>
                <rule e="way" k="*" v="*" zoom-min="17" zoom-max="17">
                    <line stroke="#707070" stroke-width="1.0" />
                    <line stroke="#70d0ff" stroke-width="0.8" />
                </rule>
            </rule>
            <!-- 隧道段 / 檢查點：蘇花公路 -->
            <rule e="way" k="tunnel" v="true|yes">
                <rule e="way" k="*" v="*" zoom-min="8" zoom-max="11">
                    <line stroke="#70d0ff" stroke-width="0.6" />
                </rule>
                <rule e="way" k="*" v="*" zoom-min="12" zoom-max="12">
                    <line stroke="#70d0ff" stroke-width="1.2" />
                </rule>
                <rule e="way" k="*" v="*" zoom-min="13" zoom-max="13">
                    <line stroke="#70d0ff" stroke-width="1.1" stroke-dasharray="2,4" stroke-linecap="square" />
                </rule>
                <rule e="way" k="*" v="*" zoom-min="14" zoom-max="14">
                    <line stroke="#70d0ff" stroke-width="1.0" stroke-dasharray="6,6" stroke-linecap="square" />
                </rule>
                <rule e="way" k="*" v="*" zoom-min="15" zoom-max="15">
                    <line stroke="#70d0ff" stroke-width="0.9" stroke-dasharray="8,8" stroke-linecap="square" />
                </rule>
                <rule e="way" k="*" v="*" zoom-min="16" zoom-max="16">
                    <line stroke="#70d0ff" stroke-width="0.8" stroke-dasharray="10,10" stroke-linecap="square" />
                </rule>
                <rule e="way" k="*" v="*" zoom-min="17" zoom-max="17">
                    <line stroke="#70d0ff" stroke-width="0.7" stroke-dasharray="12,12" stroke-linecap="square" />
                </rule>
            </rule>
            <rule e="way" k="highway" v="primary" zoom-min="10">
                <rule e="way" k="ref" v="1">
                    <lineSymbol src="assets:shields/primary/1.svg" rotate="false" align-center="true" repeat="true" />
                </rule>
                <rule e="way" k="ref" v="2">
                    <lineSymbol src="assets:shields/primary/2.svg" rotate="false" align-center="true" repeat="true" />
                </rule>
                <rule e="way" k="ref" v="3">
                    <lineSymbol src="assets:shields/primary/3.svg" rotate="false" align-center="true" repeat="true" />
                </rule>
                <rule e="way" k="ref" v="4">
                    <lineSymbol src="assets:shields/primary/4.svg" rotate="false" align-center="true" repeat="true" />
                </rule>
                <rule e="way" k="ref" v="5">
                    <lineSymbol src="assets:shields/primary/5.svg" rotate="false" align-center="true" repeat="true" />
                </rule>
                <rule e="way" k="ref" v="6">
                    <lineSymbol src="assets:shields/primary/6.svg" rotate="false" align-center="true" repeat="true" />
                </rule>
                <rule e="way" k="ref" v="7">
                    <lineSymbol src="assets:shields/primary/7.svg" rotate="false" align-center="true" repeat="true" />
                </rule>
                <rule e="way" k="ref" v="8">
                    <lineSymbol src="assets:shields/primary/8.svg" rotate="false" align-center="true" repeat="true" />
                </rule>
                <rule e="way" k="ref" v="9">
                    <lineSymbol src="assets:shields/primary/9.svg" rotate="false" align-center="true" repeat="true" />
                </rule>
                <rule e="way" k="ref" v="10">
                    <lineSymbol src="assets:shields/primary/10.svg" rotate="false" align-center="true" repeat="true" />
                </rule>
                <rule e="way" k="ref" v="11">
                    <lineSymbol src="assets:shields/primary/11.svg" rotate="false" align-center="true" repeat="true" />
                </rule>
                <rule e="way" k="ref" v="12">
                    <lineSymbol src="assets:shields/primary/12.svg" rotate="false" align-center="true" repeat="true" />
                </rule>
                <rule e="way" k="ref" v="13">
                    <lineSymbol src="assets:shields/primary/13.svg" rotate="false" align-center="true" repeat="true" />
                </rule>
                <rule e="way" k="ref" v="14">
                    <lineSymbol src="assets:shields/primary/14.svg" rotate="false" align-center="true" repeat="true" />
                </rule>
                <rule e="way" k="ref" v="15">
                    <lineSymbol src="assets:shields/primary/15.svg" rotate="false" align-center="true" repeat="true" />
                </rule>
                <rule e="way" k="ref" v="16">
                    <lineSymbol src="assets:shields/primary/16.svg" rotate="false" align-center="true" repeat="true" />
                </rule>
                <rule e="way" k="ref" v="17">
                    <lineSymbol src="assets:shields/primary/17.svg" rotate="false" align-center="true" repeat="true" />
                </rule>
                <rule e="way" k="ref" v="18">
                    <lineSymbol src="assets:shields/primary/18.svg" rotate="false" align-center="true" repeat="true" />
                </rule>
                <rule e="way" k="ref" v="19">
                    <lineSymbol src="assets:shields/primary/19.svg" rotate="false" align-center="true" repeat="true" />
                </rule>
                <rule e="way" k="ref" v="20">
                    <lineSymbol src="assets:shields/primary/20.svg" rotate="false" align-center="true" repeat="true" />
                </rule>
                <rule e="way" k="ref" v="21">
                    <lineSymbol src="assets:shields/primary/21.svg" rotate="false" align-center="true" repeat="true" />
                </rule>
                <rule e="way" k="ref" v="22">
                    <lineSymbol src="assets:shields/primary/22.svg" rotate="false" align-center="true" repeat="true" />
                </rule>
                <rule e="way" k="ref" v="23">
                    <lineSymbol src="assets:shields/primary/23.svg" rotate="false" align-center="true" repeat="true" />
                </rule>
                <rule e="way" k="ref" v="24">
                    <lineSymbol src="assets:shields/primary/24.svg" rotate="false" align-center="true" repeat="true" />
                </rule>
                <rule e="way" k="ref" v="25">
                    <lineSymbol src="assets:shields/primary/25.svg" rotate="false" align-center="true" repeat="true" />
                </rule>
                <rule e="way" k="ref" v="26">
                    <lineSymbol src="assets:shields/primary/26.svg" rotate="false" align-center="true" repeat="true" />
                </rule>
                <rule e="way" k="ref" v="27">
                    <lineSymbol src="assets:shields/primary/27.svg" rotate="false" align-center="true" repeat="true" />
                </rule>
                <rule e="way" k="ref" v="28">
                    <lineSymbol src="assets:shields/primary/28.svg" rotate="false" align-center="true" repeat="true" />
                </rule>
                <rule e="way" k="ref" v="29">
                    <lineSymbol src="assets:shields/primary/29.svg" rotate="false" align-center="true" repeat="true" />
                </rule>
                <rule e="way" k="ref" v="30">
                    <lineSymbol src="assets:shields/primary/30.svg" rotate="false" align-center="true" repeat="true" />
                </rule>
                <rule e="way" k="ref" v="31">
                    <lineSymbol src="assets:shields/primary/31.svg" rotate="false" align-center="true" repeat="true" />
                </rule>
                <rule e="way" k="ref" v="35">
                    <lineSymbol src="assets:shields/primary/35.svg" rotate="false" align-center="true" repeat="true" />
                </rule>
                <rule e="way" k="ref" v="37">
                    <lineSymbol src="assets:shields/primary/37.svg" rotate="false" align-center="true" repeat="true" />
                </rule>
                <rule e="way" k="ref" v="39">
                    <lineSymbol src="assets:shields/primary/39.svg" rotate="false" align-center="true" repeat="true" />
                </rule>
                <rule e="way" k="ref" v="63">
                    <lineSymbol src="assets:shields/primary/63.svg" rotate="false" align-center="true" repeat="true" />
                </rule>
                <rule e="way" k="ref" v="1甲">
                    <lineSymbol src="assets:shields/primary/branches/1A.svg" rotate="false" align-center="true" repeat="true" />
                </rule>
                <rule e="way" k="ref" v="1乙">
                    <lineSymbol src="assets:shields/primary/branches/1B.svg" rotate="false" align-center="true" repeat="true" />
                </rule>
                <rule e="way" k="ref" v="1丙">
                    <lineSymbol src="assets:shields/primary/branches/1C.svg" rotate="false" align-center="true" repeat="true" />
                </rule>
                <rule e="way" k="ref" v="1丁">
                    <lineSymbol src="assets:shields/primary/branches/1D.svg" rotate="false" align-center="true" repeat="true" />
                </rule>
                <rule e="way" k="ref" v="1戊">
                    <lineSymbol src="assets:shields/primary/branches/1E.svg" rotate="false" align-center="true" repeat="true" />
                </rule>
                <rule e="way" k="ref" v="1己">
                    <lineSymbol src="assets:shields/primary/branches/1F.svg" rotate="false" align-center="true" repeat="true" />
                </rule>
                <rule e="way" k="ref" v="2甲">
                    <lineSymbol src="assets:shields/primary/branches/2A.svg" rotate="false" align-center="true" repeat="true" />
                </rule>
                <rule e="way" k="ref" v="2乙">
                    <lineSymbol src="assets:shields/primary/branches/2B.svg" rotate="false" align-center="true" repeat="true" />
                </rule>
                <rule e="way" k="ref" v="2丙">
                    <lineSymbol src="assets:shields/primary/branches/2C.svg" rotate="false" align-center="true" repeat="true" />
                </rule>
                <rule e="way" k="ref" v="2丁">
                    <lineSymbol src="assets:shields/primary/branches/2D.svg" rotate="false" align-center="true" repeat="true" />
                </rule>
                <rule e="way" k="ref" v="2戊">
                    <lineSymbol src="assets:shields/primary/branches/2E.svg" rotate="false" align-center="true" repeat="true" />
                </rule>
                <rule e="way" k="ref" v="2己">
                    <lineSymbol src="assets:shields/primary/branches/2F.svg" rotate="false" align-center="true" repeat="true" />
                </rule>
                <rule e="way" k="ref" v="2庚">
                    <lineSymbol src="assets:shields/primary/branches/2G.svg" rotate="false" align-center="true" repeat="true" />
                </rule>
                <rule e="way" k="ref" v="3甲">
                    <lineSymbol src="assets:shields/primary/branches/3A.svg" rotate="false" align-center="true" repeat="true" />
                </rule>
                <rule e="way" k="ref" v="3乙">
                    <lineSymbol src="assets:shields/primary/branches/3B.svg" rotate="false" align-center="true" repeat="true" />
                </rule>
                <rule e="way" k="ref" v="3丙">
                    <lineSymbol src="assets:shields/primary/branches/3C.svg" rotate="false" align-center="true" repeat="true" />
                </rule>
                <rule e="way" k="ref" v="5甲">
                    <lineSymbol src="assets:shields/primary/branches/5A.svg" rotate="false" align-center="true" repeat="true" />
                </rule>
                <rule e="way" k="ref" v="5乙">
                    <lineSymbol src="assets:shields/primary/branches/5B.svg" rotate="false" align-center="true" repeat="true" />
                </rule>
                <rule e="way" k="ref" v="7甲">
                    <lineSymbol src="assets:shields/primary/branches/7A.svg" rotate="false" align-center="true" repeat="true" />
                </rule>
                <rule e="way" k="ref" v="7乙">
                    <lineSymbol src="assets:shields/primary/branches/7B.svg" rotate="false" align-center="true" repeat="true" />
                </rule>
                <rule e="way" k="ref" v="7丙">
                    <lineSymbol src="assets:shields/primary/branches/7C.svg" rotate="false" align-center="true" repeat="true" />
                </rule>
                <rule e="way" k="ref" v="7丁">
                    <lineSymbol src="assets:shields/primary/branches/7D.svg" rotate="false" align-center="true" repeat="true" />
                </rule>
                <rule e="way" k="ref" v="8甲">
                    <lineSymbol src="assets:shields/primary/branches/8A.svg" rotate="false" align-center="true" repeat="true" />
                </rule>
                <rule e="way" k="ref" v="9甲">
                    <lineSymbol src="assets:shields/primary/branches/9A.svg" rotate="false" align-center="true" repeat="true" />
                </rule>
                <rule e="way" k="ref" v="9乙">
                    <lineSymbol src="assets:shields/primary/branches/9B.svg" rotate="false" align-center="true" repeat="true" />
                </rule>
                <rule e="way" k="ref" v="9丙">
                    <lineSymbol src="assets:shields/primary/branches/9C.svg" rotate="false" align-center="true" repeat="true" />
                </rule>
                <rule e="way" k="ref" v="10乙">
                    <lineSymbol src="assets:shields/primary/branches/10B.svg" rotate="false" align-center="true" repeat="true" />
                </rule>
                <rule e="way" k="ref" v="11甲">
                    <lineSymbol src="assets:shields/primary/branches/11A.svg" rotate="false" align-center="true" repeat="true" />
                </rule>
                <rule e="way" k="ref" v="11乙">
                    <lineSymbol src="assets:shields/primary/branches/11B.svg" rotate="false" align-center="true" repeat="true" />
                </rule>
                <rule e="way" k="ref" v="11丙">
                    <lineSymbol src="assets:shields/primary/branches/11C.svg" rotate="false" align-center="true" repeat="true" />
                </rule>
                <rule e="way" k="ref" v="13甲">
                    <lineSymbol src="assets:shields/primary/branches/11A.svg" rotate="false" align-center="true" repeat="true" />
                </rule>
                <rule e="way" k="ref" v="14甲">
                    <lineSymbol src="assets:shields/primary/branches/14A.svg" rotate="false" align-center="true" repeat="true" />
                </rule>
                <rule e="way" k="ref" v="14乙">
                    <lineSymbol src="assets:shields/primary/branches/14B.svg" rotate="false" align-center="true" repeat="true" />
                </rule>
                <rule e="way" k="ref" v="14丙">
                    <lineSymbol src="assets:shields/primary/branches/14C.svg" rotate="false" align-center="true" repeat="true" />
                </rule>
                <rule e="way" k="ref" v="14丁">
                    <lineSymbol src="assets:shields/primary/branches/14D.svg" rotate="false" align-center="true" repeat="true" />
                </rule>
                <rule e="way" k="ref" v="15甲">
                    <lineSymbol src="assets:shields/primary/branches/15A.svg" rotate="false" align-center="true" repeat="true" />
                </rule>
                <rule e="way" k="ref" v="17甲">
                    <lineSymbol src="assets:shields/primary/branches/17A.svg" rotate="false" align-center="true" repeat="true" />
                </rule>
                <rule e="way" k="ref" v="17乙">
                    <lineSymbol src="assets:shields/primary/branches/17B.svg" rotate="false" align-center="true" repeat="true" />
                </rule>
                <rule e="way" k="ref" v="19甲">
                    <lineSymbol src="assets:shields/primary/branches/19A.svg" rotate="false" align-center="true" repeat="true" />
                </rule>
                <rule e="way" k="ref" v="20甲">
                    <lineSymbol src="assets:shields/primary/branches/20A.svg" rotate="false" align-center="true" repeat="true" />
                </rule>
                <rule e="way" k="ref" v="20乙">
                    <lineSymbol src="assets:shields/primary/branches/20B.svg" rotate="false" align-center="true" repeat="true" />
                </rule>
                <rule e="way" k="ref" v="21甲">
                    <lineSymbol src="assets:shields/primary/branches/21A.svg" rotate="false" align-center="true" repeat="true" />
                </rule>
                <rule e="way" k="ref" v="27甲">
                    <lineSymbol src="assets:shields/primary/branches/27A.svg" rotate="false" align-center="true" repeat="true" />
                </rule>
                <rule e="way" k="ref" v="63甲">
                    <lineSymbol src="assets:shields/primary/branches/63A.svg" rotate="false" align-center="true" repeat="true" />
                </rule>
                <rule e="way" k="ref" v="68甲">
                    <lineSymbol src="assets:shields/primary/branches/68A.svg" rotate="false" align-center="true" repeat="true" />
                </rule>
                <rule e="way" k="ref" v="74甲">
                    <lineSymbol src="assets:shields/primary/branches/74A.svg" rotate="false" align-center="true" repeat="true" />
                </rule>
                <!--
                共線路段:
                    SELECT DISTINCT ref FROM planet_osm_line
                    WHERE highway='primary'
                    AND ref LIKE '%;%'
                    ORDER BY ref;
                -->
                <rule e="way" k="ref" v="1;106甲">
                    <lineSymbol src="assets:shields/primary/1.svg" rotate="false" align-center="true" repeat="true" />
                </rule>
                <rule e="way" k="ref" v="1;110甲">
                    <lineSymbol src="assets:shields/primary/1.svg" rotate="false" align-center="true" repeat="true" />
                </rule>
                <rule e="way" k="ref" v="1;112">
                    <lineSymbol src="assets:shields/primary/1.svg" rotate="false" align-center="true" repeat="true" />
                </rule>
                <rule e="way" k="ref" v="1;117">
                    <lineSymbol src="assets:shields/primary/1.svg" rotate="false" align-center="true" repeat="true" />
                </rule>
                <rule e="way" k="ref" v="1;158甲">
                    <lineSymbol src="assets:shields/primary/1.svg" rotate="false" align-center="true" repeat="true" />
                </rule>
                <rule e="way" k="ref" v="1;19甲">
                    <lineSymbol src="assets:shields/primary/1.svg" rotate="false" align-center="true" repeat="true" />
                </rule>
                <rule e="way" k="ref" v="1;1甲">
                    <!-- 捷運新莊站附近 -->
                    <lineSymbol src="assets:shields/primary/1.svg" rotate="false" align-center="true" repeat="true" />
                </rule>
                <rule e="way" k="ref" v="1;3">
                    <lineSymbol src="assets:shields/primary/1.svg" rotate="false" align-center="true" repeat="true" />
                </rule>
                <rule e="way" k="ref" v="1;4">
                    <lineSymbol src="assets:shields/primary/1.svg" rotate="false" align-center="true" repeat="true" />
                </rule>
                <rule e="way" k="ref" v="1;4;110">
                    <lineSymbol src="assets:shields/primary/1.svg" rotate="false" align-center="true" repeat="true" />
                </rule>
                <rule e="way" k="ref" v="1;桃11">
                    <lineSymbol src="assets:shields/primary/1.svg" rotate="false" align-center="true" repeat="true" />
                </rule>
                <rule e="way" k="ref" v="1;雲42">
                    <lineSymbol src="assets:shields/primary/1.svg" rotate="false" align-center="true" repeat="true" />
                </rule>
                <rule e="way" k="ref" v="1;雲49">
                    <lineSymbol src="assets:shields/primary/1.svg" rotate="false" align-center="true" repeat="true" />
                </rule>
                <rule e="way" k="ref" v="1;嘉88">
                    <lineSymbol src="assets:shields/primary/1.svg" rotate="false" align-center="true" repeat="true" />
                </rule>
                <rule e="way" k="ref" v="1甲;104">
                    <lineSymbol src="assets:shields/primary/branches/1A.svg" rotate="false" align-center="true" repeat="true" />
                </rule>
                <rule e="way" k="ref" v="1甲;106">
                    <lineSymbol src="assets:shields/primary/branches/1A.svg" rotate="false" align-center="true" repeat="true" />
                </rule>
                <rule e="way" k="ref" v="2;2乙">
                    <lineSymbol src="assets:shields/primary/2.svg" rotate="false" align-center="true" repeat="true" />
                </rule>
                <rule e="way" k="ref" v="2;2戊">
                    <lineSymbol src="assets:shields/primary/2.svg" rotate="false" align-center="true" repeat="true" />
                </rule>
                <rule e="way" k="ref" v="2丙;102">
                    <lineSymbol src="assets:shields/primary/branches/2C.svg" rotate="false" align-center="true" repeat="true" />
                </rule>
                <rule e="way" k="ref" v="3;106">
                    <lineSymbol src="assets:shields/primary/3.svg" rotate="false" align-center="true" repeat="true" />
                </rule>
                <rule e="way" k="ref" v="3;110">
                    <lineSymbol src="assets:shields/primary/3.svg" rotate="false" align-center="true" repeat="true" />
                </rule>
                <rule e="way" k="ref" v="3;114">
                    <lineSymbol src="assets:shields/primary/3.svg" rotate="false" align-center="true" repeat="true" />
                </rule>
                <rule e="way" k="ref" v="3;120">
                    <lineSymbol src="assets:shields/primary/3.svg" rotate="false" align-center="true" repeat="true" />
                </rule>
                <rule e="way" k="ref" v="3;124">
                    <lineSymbol src="assets:shields/primary/3.svg" rotate="false" align-center="true" repeat="true" />
                </rule>
                <rule e="way" k="ref" v="3;152">
                    <lineSymbol src="assets:shields/primary/3.svg" rotate="false" align-center="true" repeat="true" />
                </rule>
                <rule e="way" k="ref" v="3;20">
                    <lineSymbol src="assets:shields/primary/3.svg" rotate="false" align-center="true" repeat="true" />
                </rule>
                <rule e="way" k="ref" v="3;22">
                    <lineSymbol src="assets:shields/primary/3.svg" rotate="false" align-center="true" repeat="true" />
                </rule>
                <rule e="way" k="ref" v="3;28;29">
                    <lineSymbol src="assets:shields/primary/3.svg" rotate="false" align-center="true" repeat="true" />
                </rule>
                <rule e="way" k="ref" v="3;29">
                    <lineSymbol src="assets:shields/primary/3.svg" rotate="false" align-center="true" repeat="true" />
                </rule>
                <rule e="way" k="ref" v="3;4">
                    <lineSymbol src="assets:shields/primary/3.svg" rotate="false" align-center="true" repeat="true" />
                </rule>
                <rule e="way" k="ref" v="3;竹37">
                    <lineSymbol src="assets:shields/primary/3.svg" rotate="false" align-center="true" repeat="true" />
                </rule>
                <rule e="way" k="ref" v="3;桃64">
                    <lineSymbol src="assets:shields/primary/3.svg" rotate="false" align-center="true" repeat="true" />
                </rule>
                <rule e="way" k="ref" v="6;苗24">
                    <lineSymbol src="assets:shields/primary/6.svg" rotate="false" align-center="true" repeat="true" />
                </rule>
                <rule e="way" k="ref" v="7;宜18">
                    <lineSymbol src="assets:shields/primary/7.svg" rotate="false" align-center="true" repeat="true" />
                </rule>
                <rule e="way" k="ref" v="7;宜7">
                    <lineSymbol src="assets:shields/primary/7.svg" rotate="false" align-center="true" repeat="true" />
                </rule>
                <rule e="way" k="ref" v="9;30">
                    <lineSymbol src="assets:shields/primary/9.svg" rotate="false" align-center="true" repeat="true" />
                </rule>
                <rule e="way" k="ref" v="11;193">
                    <lineSymbol src="assets:shields/primary/11.svg" rotate="false" align-center="true" repeat="true" />
                </rule>
                <rule e="way" k="ref" v="11;花29">
                    <lineSymbol src="assets:shields/primary/11.svg" rotate="false" align-center="true" repeat="true" />
                </rule>
                <rule e="way" k="ref" v="11甲;193">
                    <lineSymbol src="assets:shields/primary/branches/11A.svg" rotate="false" align-center="true" repeat="true" />
                </rule>
                <rule e="way" k="ref" v="13;119">
                    <lineSymbol src="assets:shields/primary/13.svg" rotate="false" align-center="true" repeat="true" />
                </rule>
                <rule e="way" k="ref" v="13甲;124">
                    <lineSymbol src="assets:shields/primary/branches/13A.svg" rotate="false" align-center="true" repeat="true" />
                </rule>
                <rule e="way" k="ref" v="14;21">
                    <lineSymbol src="assets:shields/primary/14.svg" rotate="false" align-center="true" repeat="true" />
                </rule>
                <rule e="way" k="ref" v="14;投6">
                    <lineSymbol src="assets:shields/primary/14.svg" rotate="false" align-center="true" repeat="true" />
                </rule>
                <rule e="way" k="ref" v="15;桃35">
                    <lineSymbol src="assets:shields/primary/15.svg" rotate="false" align-center="true" repeat="true" />
                </rule>
                <rule e="way" k="ref" v="15;桃37">
                    <lineSymbol src="assets:shields/primary/15.svg" rotate="false" align-center="true" repeat="true" />
                </rule>
                <rule e="way" k="ref" v="15;桃96">
                    <lineSymbol src="assets:shields/primary/15.svg" rotate="false" align-center="true" repeat="true" />
                </rule>
                <rule e="way" k="ref" v="15;竹市2">
                    <lineSymbol src="assets:shields/primary/15.svg" rotate="false" align-center="true" repeat="true" />
                </rule>
                <rule e="way" k="ref" v="16;152">
                    <lineSymbol src="assets:shields/primary/16.svg" rotate="false" align-center="true" repeat="true" />
                </rule>
                <rule e="way" k="ref" v="16;21">
                    <lineSymbol src="assets:shields/primary/16.svg" rotate="false" align-center="true" repeat="true" />
                </rule>
                <rule e="way" k="ref" v="17;嘉18">
                    <lineSymbol src="assets:shields/primary/17.svg" rotate="false" align-center="true" repeat="true" />
                </rule>
                <rule e="way" k="ref" v="17甲;高4">
                    <lineSymbol src="assets:shields/primary/branches/17A.svg" rotate="false" align-center="true" repeat="true" />
                </rule>
                <rule e="way" k="ref" v="18;嘉64">
                    <lineSymbol src="assets:shields/primary/18.svg" rotate="false" align-center="true" repeat="true" />
                </rule>
                <rule e="way" k="ref" v="19;139">
                    <lineSymbol src="assets:shields/primary/19.svg" rotate="false" align-center="true" repeat="true" />
                </rule>
                <rule e="way" k="ref" v="19;152">
                    <lineSymbol src="assets:shields/primary/19.svg" rotate="false" align-center="true" repeat="true" />
                </rule>
                <rule e="way" k="ref" v="19;154">
                    <lineSymbol src="assets:shields/primary/19.svg" rotate="false" align-center="true" repeat="true" />
                </rule>
                <rule e="way" k="ref" v="19;彰130">
                    <lineSymbol src="assets:shields/primary/19.svg" rotate="false" align-center="true" repeat="true" />
                </rule>
                <rule e="way" k="ref" v="19;彰148">
                    <lineSymbol src="assets:shields/primary/19.svg" rotate="false" align-center="true" repeat="true" />
                </rule>
                <rule e="way" k="ref" v="19;雲162">
                    <lineSymbol src="assets:shields/primary/19.svg" rotate="false" align-center="true" repeat="true" />
                </rule>
                <rule e="way" k="ref" v="19;雲168">
                    <lineSymbol src="assets:shields/primary/19.svg" rotate="false" align-center="true" repeat="true" />
                </rule>
                <rule e="way" k="ref" v="19甲;182">
                    <lineSymbol src="assets:shields/primary/branches/19A.svg" rotate="false" align-center="true" repeat="true" />
                </rule>
                <rule e="way" k="ref" v="19甲;186">
                    <lineSymbol src="assets:shields/primary/branches/19A.svg" rotate="false" align-center="true" repeat="true" />
                </rule>
                <rule e="way" k="ref" v="20;29">
                    <lineSymbol src="assets:shields/primary/20.svg" rotate="false" align-center="true" repeat="true" />
                </rule>
                <rule e="way" k="ref" v="22;186">
                    <lineSymbol src="assets:shields/primary/22.svg" rotate="false" align-center="true" repeat="true" />
                </rule>
                <rule e="way" k="ref" v="24;185">
                    <lineSymbol src="assets:shields/primary/24.svg" rotate="false" align-center="true" repeat="true" />
                </rule>
                <rule e="way" k="ref" v="27;17">
                    <lineSymbol src="assets:shields/primary/27.svg" rotate="false" align-center="true" repeat="true" />
                </rule>
                <rule e="way" k="ref" v="28;181">
                    <lineSymbol src="assets:shields/primary/28.svg" rotate="false" align-center="true" repeat="true" />
                </rule>
                <rule e="way" k="ref" v="28;高140">
                    <lineSymbol src="assets:shields/primary/28.svg" rotate="false" align-center="true" repeat="true" />
                </rule>
                <rule e="way" k="ref" v="31;桃102">
                    <lineSymbol src="assets:shields/primary/31.svg" rotate="false" align-center="true" repeat="true" />
                </rule>
                <rule e="way" k="ref" v="37;157">
                    <lineSymbol src="assets:shields/primary/37.svg" rotate="false" align-center="true" repeat="true" />
                </rule>
            </rule>
        </rule>

        <!-- 快速道路 -->
        <rule e="way" k="highway" v="trunk|trunk_link">
            <!-- 除錯用 -->
            <rule e="way" k="*" v="*" zoom-min="8" zoom-max="18">
                <pathText k="name" fill="#000000" font-size="10" stroke="#ffffff" stroke-width="2.0" />
            </rule>
            <!-- 非隧道段 -->
            <rule e="way" k="tunnel" v="~|no|false">
                <rule e="way" k="*" v="*" zoom-min="8" zoom-max="9">
                    <line stroke="#f0b0b0" stroke-width="0.6" />
                </rule>
                <rule e="way" k="*" v="*" zoom-min="10" zoom-max="12">
                    <line stroke="#f0b0b0" stroke-width="0.9" />
                </rule>
                <rule e="way" k="*" v="*" zoom-min="13" zoom-max="15">
                    <line stroke="#707070" stroke-width="1.2" />
                    <line stroke="#f0b0b0" stroke-width="1.0" />
                </rule>
                <rule e="way" k="*" v="*" zoom-min="16" zoom-max="16">
                    <line stroke="#707070" stroke-width="0.9" />
                    <line stroke="#f0b0b0" stroke-width="0.7" />
                </rule>
                <rule e="way" k="*" v="*" zoom-min="17" zoom-max="17">
                    <line stroke="#707070" stroke-width="1.0" />
                    <line stroke="#f0b0b0" stroke-width="0.8" />
                </rule>
            </rule>
            <!-- 隧道段 / 檢查點：觀音山隧道-->
            <rule e="way" k="tunnel" v="true|yes">
                <rule e="way" k="*" v="*" zoom-min="8" zoom-max="11">
                    <line stroke="#f0b0b0" stroke-width="0.6" />
                </rule>
                <rule e="way" k="*" v="*" zoom-min="12" zoom-max="12">
                    <line stroke="#f0b0b0" stroke-width="1.2" />
                </rule>
                <rule e="way" k="*" v="*" zoom-min="13" zoom-max="13">
                    <line stroke="#f0b0b0" stroke-width="1.1" stroke-dasharray="2,4" stroke-linecap="square" />
                </rule>
                <rule e="way" k="*" v="*" zoom-min="14" zoom-max="14">
                    <line stroke="#f0b0b0" stroke-width="1.0" stroke-dasharray="6,6" stroke-linecap="square" />
                </rule>
                <rule e="way" k="*" v="*" zoom-min="15" zoom-max="15">
                    <line stroke="#f0b0b0" stroke-width="0.9" stroke-dasharray="8,8" stroke-linecap="square" />
                </rule>
                <rule e="way" k="*" v="*" zoom-min="16" zoom-max="16">
                    <line stroke="#f0b0b0" stroke-width="0.8" stroke-dasharray="10,10" stroke-linecap="square" />
                </rule>
                <rule e="way" k="*" v="*" zoom-min="17" zoom-max="17">
                    <line stroke="#f0b0b0" stroke-width="0.7" stroke-dasharray="12,12" stroke-linecap="square" />
                </rule>
            </rule>
            <rule e="way" k="*" v="*" zoom-min="8">
                <rule e="way" k="ref" v="61">
                    <lineSymbol src="assets:shields/trunk/61.svg" rotate="false" align-center="true" repeat="true" />
                </rule>
                <rule e="way" k="ref" v="62">
                    <lineSymbol src="assets:shields/trunk/62.svg" rotate="false" align-center="true" repeat="true" />
                </rule>
                <rule e="way" k="ref" v="64">
                    <lineSymbol src="assets:shields/trunk/64.svg" rotate="false" align-center="true" repeat="true" />
                </rule>
                <rule e="way" k="ref" v="65">
                    <lineSymbol src="assets:shields/trunk/65.svg" rotate="false" align-center="true" repeat="true" />
                </rule>
                <rule e="way" k="ref" v="66">
                    <lineSymbol src="assets:shields/trunk/66.svg" rotate="false" align-center="true" repeat="true" />
                </rule>
                <rule e="way" k="ref" v="68">
                    <lineSymbol src="assets:shields/trunk/68.svg" rotate="false" align-center="true" repeat="true" />
                </rule>
                <rule e="way" k="ref" v="72">
                    <lineSymbol src="assets:shields/trunk/72.svg" rotate="false" align-center="true" repeat="true" />
                </rule>
                <rule e="way" k="ref" v="74">
                    <lineSymbol src="assets:shields/trunk/74.svg" rotate="false" align-center="true" repeat="true" />
                </rule>
                <rule e="way" k="ref" v="76">
                    <lineSymbol src="assets:shields/trunk/76.svg" rotate="false" align-center="true" repeat="true" />
                </rule>
                <rule e="way" k="ref" v="78">
                    <lineSymbol src="assets:shields/trunk/78.svg" rotate="false" align-center="true" repeat="true" />
                </rule>
                <rule e="way" k="ref" v="82">
                    <lineSymbol src="assets:shields/trunk/82.svg" rotate="false" align-center="true" repeat="true" />
                </rule>
                <rule e="way" k="ref" v="84">
                    <lineSymbol src="assets:shields/trunk/84.svg" rotate="false" align-center="true" repeat="true" />
                </rule>
                <rule e="way" k="ref" v="86">
                    <lineSymbol src="assets:shields/trunk/86.svg" rotate="false" align-center="true" repeat="true" />
                </rule>
                <rule e="way" k="ref" v="88">
                    <lineSymbol src="assets:shields/trunk/88.svg" rotate="false" align-center="true" repeat="true" />
                </rule>
                <rule e="way" k="ref" v="61甲">
                    <lineSymbol src="assets:shields/trunk/branches/61A.svg" rotate="false" align-center="true" repeat="true" />
                </rule>
                <rule e="way" k="ref" v="61乙">
                    <lineSymbol src="assets:shields/trunk/branches/61B.svg" rotate="false" align-center="true" repeat="true" />
                </rule>
            </rule>
        </rule>

        <!-- 高速公路 -->
        <rule e="way" k="highway" v="motorway|motorway_link">
            <!-- 除錯用 -->
            <rule e="way" k="*" v="*" zoom-min="8" zoom-max="18">
                <pathText k="name" fill="#000000" font-size="10" stroke="#ffffff" stroke-width="2.0" />
            </rule>
            <!-- 非隧道段 -->
            <rule e="way" k="tunnel" v="~|no|false">
                <rule e="way" k="*" v="*" zoom-min="8" zoom-max="9">
                    <line stroke="#80a080" stroke-width="0.6" />
                </rule>
                <rule e="way" k="*" v="*" zoom-min="10" zoom-max="12">
                    <line stroke="#a0c0a0" stroke-width="0.9" />
                </rule>
                <rule e="way" k="*" v="*" zoom-min="13" zoom-max="15">
                    <line stroke="#707070" stroke-width="1.2" />
                    <line stroke="#a0c0a0" stroke-width="1.0" />
                </rule>
                <rule e="way" k="*" v="*" zoom-min="16" zoom-max="16">
                    <line stroke="#707070" stroke-width="0.9" />
                    <line stroke="#a0c0a0" stroke-width="0.7" />
                </rule>
                <rule e="way" k="*" v="*" zoom-min="17" zoom-max="17">
                    <line stroke="#707070" stroke-width="1.0" />
                    <line stroke="#a0c0a0" stroke-width="0.8" />
                </rule>
            </rule>
            <!-- 隧道段 / 檢查點：雪山隧道-->
            <rule e="way" k="tunnel" v="true|yes">
                <rule e="way" k="*" v="*" zoom-min="8" zoom-max="11">
                    <line stroke="#a0c0a0" stroke-width="0.6" />
                </rule>
                <rule e="way" k="*" v="*" zoom-min="12" zoom-max="12">
                    <line stroke="#a0c0a0" stroke-width="1.2" />
                </rule>
                <rule e="way" k="*" v="*" zoom-min="13" zoom-max="13">
                    <line stroke="#a0c0a0" stroke-width="1.1" stroke-dasharray="2,4" stroke-linecap="square" />
                </rule>
                <rule e="way" k="*" v="*" zoom-min="14" zoom-max="14">
                    <line stroke="#a0c0a0" stroke-width="1.0" stroke-dasharray="6,6" stroke-linecap="square" />
                </rule>
                <rule e="way" k="*" v="*" zoom-min="15" zoom-max="15">
                    <line stroke="#a0c0a0" stroke-width="0.9" stroke-dasharray="8,8" stroke-linecap="square" />
                </rule>
                <rule e="way" k="*" v="*" zoom-min="16" zoom-max="16">
                    <line stroke="#a0c0a0" stroke-width="0.8" stroke-dasharray="10,10" stroke-linecap="square" />
                </rule>
                <rule e="way" k="*" v="*" zoom-min="17" zoom-max="17">
                    <line stroke="#a0c0a0" stroke-width="0.7" stroke-dasharray="12,12" stroke-linecap="square" />
                </rule>
            </rule>
            <!-- 標誌 -->
            <rule e="way" k="highway" v="motorway" zoom-min="8" zoom-max="18">
                <rule e="way" k="ref" v="1">
                    <lineSymbol src="assets:shields/motorway/1.svg"
                        symbol-percent="85" rotate="false" align-center="true"
                        repeat="true" repeat-start="5" repeat-gap="250" />
                </rule>
                <rule e="way" k="ref" v="2">
                    <lineSymbol src="assets:shields/motorway/2.svg"
                        symbol-percent="85" rotate="false" align-center="true"
                        repeat="true" repeat-start="5" repeat-gap="250" />
                </rule>
                <rule e="way" k="ref" v="3">
                    <lineSymbol src="assets:shields/motorway/3.svg"
                        symbol-percent="85" rotate="false" align-center="true"
                        repeat="true" repeat-start="5" repeat-gap="250" />
                </rule>
                <rule e="way" k="ref" v="4">
                    <lineSymbol src="assets:shields/motorway/4.svg"
                        symbol-percent="85" rotate="false" align-center="true"
                        repeat="true" repeat-start="5" repeat-gap="250" />
                </rule>
                <rule e="way" k="ref" v="5">
                    <lineSymbol src="assets:shields/motorway/5.svg"
                        symbol-percent="85" rotate="false" align-center="true"
                        repeat="true" repeat-start="5" repeat-gap="250" />
                </rule>
                <rule e="way" k="ref" v="6">
                    <lineSymbol src="assets:shields/motorway/6.svg"
                        symbol-percent="85" rotate="false" align-center="true"
                        repeat="true" repeat-start="5" repeat-gap="250" />
                </rule>
                <rule e="way" k="ref" v="8">
                    <lineSymbol src="assets:shields/motorway/8.svg"
                        symbol-percent="85" rotate="false" align-center="true"
                        repeat="true" repeat-start="5" repeat-gap="250" />
                </rule>
                <rule e="way" k="ref" v="10">
                    <lineSymbol src="assets:shields/motorway/10.svg"
                        symbol-percent="85" rotate="false" align-center="true"
                        repeat="true" repeat-start="5" repeat-gap="250" />
                </rule>
                <rule e="way" k="ref" v="2甲">
                    <lineSymbol src="assets:shields/motorway/branches/2A.svg"
                        symbol-percent="85" rotate="false" align-center="true"
                        repeat="true" repeat-start="5" repeat-gap="250" />
                </rule>
                <rule e="way" k="ref" v="3甲">
                    <lineSymbol src="assets:shields/motorway/branches/3A.svg"
                        symbol-percent="85" rotate="false" align-center="true"
                        repeat="true" repeat-start="5" repeat-gap="250" />
                </rule>
            </rule>
        </rule>
    </rule>

    <!-- 高鐵、台鐵、捷運 -->
    <rule e="way" k="railway" v="*">
        <rule e="way" k="railway" v="rail">
            <!-- 高鐵 (因缺少 highspeed 欄位暫時無效) -->
            <rule e="way" k="highspeed" v="yes">
                <rule e="way" k="*" v="*" zoom-min="8" zoom-max="9">
                    <line stroke="#707070" stroke-width="0.6" />
                    <line stroke="#ffffff" stroke-width="0.4" stroke-dasharray="6,6" stroke-linecap="butt" />
                </rule>
                <rule e="way" k="*" v="*" zoom-min="10" zoom-max="12">
                    <line stroke="#707070" stroke-width="0.8" />
                    <line stroke="#ffffff" stroke-width="0.6" stroke-dasharray="8,8" stroke-linecap="butt" />
                </rule>
                <rule e="way" k="*" v="*" zoom-min="13" zoom-max="15">
                    <line stroke="#707070" stroke-width="1.0" />
                    <line stroke="#ffffff" stroke-width="0.7" stroke-dasharray="10,10" stroke-linecap="butt" />
                </rule>
                <rule e="way" k="*" v="*" zoom-min="16" zoom-max="16">
                    <line stroke="#707070" stroke-width="0.6" />
                    <line stroke="#ffffff" stroke-width="0.3" stroke-dasharray="15,15" stroke-linecap="butt" />
                </rule>
                <rule e="way" k="*" v="*" zoom-min="17" zoom-max="17">
                    <line stroke="#707070" stroke-width="0.6" />
                    <line stroke="#ffffff" stroke-width="0.3" stroke-dasharray="20,20" stroke-linecap="butt" />
                </rule>
            </rule>
            <!-- 台鐵 -->
            <rule e="way" k="highspeed" v="~|no">
                <rule e="way" k="*" v="*" zoom-min="8" zoom-max="9">
                    <line stroke="#909090" stroke-width="0.6" />
                    <line stroke="#ffffff" stroke-width="0.4" stroke-dasharray="6,6" stroke-linecap="butt" />
                </rule>
                <rule e="way" k="*" v="*" zoom-min="10" zoom-max="12">
                    <line stroke="#909090" stroke-width="0.8" />
                    <line stroke="#ffffff" stroke-width="0.6" stroke-dasharray="8,8" stroke-linecap="butt" />
                </rule>
                <rule e="way" k="*" v="*" zoom-min="13" zoom-max="15">
                    <line stroke="#909090" stroke-width="1.0" />
                    <line stroke="#ffffff" stroke-width="0.7" stroke-dasharray="10,10" stroke-linecap="butt" />
                </rule>
                <rule e="way" k="*" v="*" zoom-min="16" zoom-max="16">
                    <line stroke="#909090" stroke-width="0.6" />
                    <line stroke="#ffffff" stroke-width="0.3" stroke-dasharray="15,15" stroke-linecap="butt" />
                </rule>
                <rule e="way" k="*" v="*" zoom-min="17" zoom-max="17">
                    <line stroke="#909090" stroke-width="0.6" />
                    <line stroke="#ffffff" stroke-width="0.3" stroke-dasharray="20,20" stroke-linecap="butt" />
                </rule>
            </rule>
        </rule>
        <!-- 捷運 -->
        <rule e="way" k="railway" v="subway">
            <rule e="way" k="*" v="*" zoom-min="15" zoom-max="15">
                <line stroke="#50a0f0" stroke-width="1.0" />
                <line stroke="#ffffff" stroke-width="0.7" stroke-dasharray="10,10" stroke-linecap="butt" />
            </rule>
            <rule e="way" k="*" v="*" zoom-min="16" zoom-max="16">
                <line stroke="#50a0f0" stroke-width="0.6" />
                <line stroke="#ffffff" stroke-width="0.3" stroke-dasharray="15,15" stroke-linecap="butt" />
            </rule>
            <rule e="way" k="*" v="*" zoom-min="17" zoom-max="17">
                <line stroke="#50a0f0" stroke-width="0.6" />
                <line stroke="#ffffff" stroke-width="0.3" stroke-dasharray="20,20" stroke-linecap="butt" />
            </rule>
        </rule>
    </rule>

</rendertheme>